[
  {
    "title": "一、寫出國字或注音",
    "subtitle": "",
    "question": [
      {
        "title": "",
        "category": "vocabularyZhuyin",
        "answers": [
          "葵", "遇", "危", "準", "射", "刺", "使", "痛", "欺", "負", "感", "丑", "丑", "觸", "毒", "擺", "露", "居", "懷", "葵"
        ],
        "zhuyin": [
          ["ㄎㄨㄟˊ"], ["ㄩˋ"], ["ㄨㄟˊ"], ["ㄓㄨㄣˇ"], ["ㄕㄜˋ"], ["ㄘˋ"], ["ㄕˇ"], ["ㄊㄨㄥˋ"], ["ㄑㄧ"], ["ㄈㄨˋ"], ["ㄍㄢˇ"], ["ㄔㄡˇ"], ["ㄔㄡˇ"], ["ㄔㄨˋ"], ["ㄉㄨˊ"], ["ㄅㄞˇ"], ["ㄌㄡˋ"], ["ㄐㄩ"], ["ㄏㄨㄞˊ"], ["ㄎㄨㄟˊ"]
        ]
      }
    ]
  },
  {
    "title": "二、根據提示，填入正確國字",
    "subtitle": "",
    "question": [
      {
        "title": "",
        "category": "vocabulary",
        "answers": [
          "寓", "遇", "偶", "愚"
        ]
      }
    ]
  },
  {
    "title": "三、根據提示作答",
    "subtitle": "",
    "question": [
      {
        "title": "1",
        "category": "vocabulary",
        "answers": [
          "居心不良"
        ]
      },
      {
        "title": "2",
        "category": "vocabulary",
        "answers": [
          "✓ 好言好語"
        ]
      }
    ]
  },
  {
    "title": "四、完成句子",
    "subtitle": "",
    "question": [
      {
        "title": "1",
        "category": "vocabulary",
        "answers": [
          "就看到最喜歡吃的水果，真是開心。"
        ]
      },
      {
        "title": "2",
        "category": "vocabulary",
        "answers": [
          "選手一聽到槍聲響起，就迅速邁開大步向前跑，使比賽戰況變得激烈起來。"
        ]
      }
    ]
  },
  {
    "title": "五、根據提示，完成課文內容。",
    "subtitle": "",
    "question": [
      {
        "title": "起因",
        "category": "vocabulary",
        "answers": [
          "玩躲貓貓"
        ]
      },
      {
        "title": "經過",
        "category": "vocabulary",
        "answers": [
          "大嘴巴", "找地方躲起來", "刺針"
        ]
      }
    ]
  },
  {
    "title": "六、讀一讀，再回答問題。",
    "subtitle": "",
    "question": [
      {
        "title": "1",
        "category": "vocabulary",
        "answers": [
          "①"
        ]
      },
      {
        "title": "2",
        "category": "vocabulary",
        "answers": [
          "③"
        ]
      },
      {
        "title": "3",
        "category": "vocabulary",
        "answers": [
          "③", "①", "②"
        ]
      }
    ]
  }
]
