[
  {
    "title": "一、寫出國字或注音",
    "subtitle": "",
    "special": "noNumber",
    "question": [
      {
        "title": "",
        "category": "vocabularyZhuyin",
        "answers": [
          "職", "療", "裁", "證",
          "症", "瀏", "覽", "癒", "拜", "搜"
        ],
        "zhuyin": [
          ["ㄓˊ"], ["ㄌㄧㄠˊ"], ["ㄘㄞˊ"], ["ㄓㄥˋ"],
          ["ㄓㄥˋ"], ["ㄌㄧㄡˊ"], ["ㄌㄢˇ"], ["ㄩˋ"], ["ㄅㄞˋ"], ["ㄙㄡ"]
        ]
      },
      {
        "title": "",
        "category": "vocabulary",
        "answers": [
          "②"
        ]
      }
    ]
  },
  {
    "title": "二、依課文內容，完成問題",
    "subtitle": "",
    "question": [
      {
        "title": "背景",
        "category": "vocabulary",
        "answers": [
          "接觸並認同小丑醫生理念"
        ]
      },
      {
        "title": "資格",
        "category": "vocabulary",
        "answers": [
          "小朋友心理", "專業實習和考核"
        ]
      },
      {
        "title": "動力",
        "category": "vocabulary",
        "answers": [
          "每個病童的笑容"
        ]
      },
      {
        "title": "治療方式",
        "category": "vocabulary",
        "answers": [
          "針對每個病童客製化表演內容，到病床表演"
        ]
      }
    ]
  },
  {
    "title": "三、替換語詞",
    "subtitle": "",
    "special": "noNumber",
    "question": [
      {
        "title": "",
        "category": "vocabulary",
        "answers": [
          "獨一無二", "別出心裁", "揮汗如雨"
        ]
      }
    ]
  },
  {
    "title": "四、句型練習",
    "subtitle": "",
    "question": [
      {
        "title": "1",
        "category": "vocabulary",
        "answers": [
          "為了完成學業，她每天都堅持努力學習。", "為了準備明天的考試，我決定熬夜讀書。"
        ]
      },
      {
        "title": "2",
        "category": "vocabulary",
        "answers": [
          "我決定提前完成工作，以便有更多時間享受假期。", "他每天努力工作，以便能夠提供更好的生活條件給家人。"
        ]
      }
    ]
  },
  {
    "title": "五、閱讀並回答問題",
    "subtitle": "",
    "question": [
      {
        "title": "1",
        "category": "vocabulary",
        "answers": [
          "④"
        ]
      },
      {
        "title": "2",
        "category": "vocabulary",
        "answers": [
          "✓ 沒有病痛", "✓ 充滿歡樂", "✓ 多彩明亮"
        ]
      },
      {
        "title": "3",
        "category": "vocabulary",
        "answers": [
          "(僅供參考) 作者相信「每個人都可以是紅鼻小孩」，可能是因為他相信每個人都有帶給他人歡樂和幸福的能力。他認為，就像紅鼻小孩一樣，每個人都可以透過積極的態度和行動，為周圍的人帶來溫暖和幸福。我的看法是，這種信念體現了對人性的樂觀和對生活的積極態度。這種信念鼓勵著人們堅持希望，積極面對生活中的困難和挑戰，並且努力為周圍的人帶來溫暖和幸福。"
        ]
      }
    ]
  },
  {
    "title": "六、寫作練習",
    "subtitle": "",
    "question": [
      {
        "title": "",
        "category": "vocabulary",
        "answers": [
          "略"
        ]
      }
    ]
  }
]
